[
  {
    "home_abbr": "NYY",
    "away_abbr": "LAD",
    "home_name": "New York Yankees",
    "away_name": "Los Angeles Dodgers",
    "pick_abbr": "LAD",
    "pick": "Los Angeles Dodgers",
    "confidence": 0.6988331774532242,
    "pick_odds": -105,
    "home_pitcher": "Ryan Weathers",
    "away_pitcher": "Emmet Sheehan",
    "game_id": 823523,
    "result": null
  },
  {
    "home_abbr": "COL",
    "away_abbr": "CIN",
    "home_name": "Colorado Rockies",
    "away_name": "Cincinnati Reds",
    "pick_abbr": "CIN",
    "pick": "Cincinnati Reds",
    "confidence": 0.6735196052561376,
    "pick_odds": -113,
    "home_pitcher": "Tomoyuki Sugano",
    "away_pitcher": "Rhett Lowder",
    "game_id": 824331,
    "result": null
  },
  {
    "home_abbr": "ARI",
    "away_abbr": "STL",
    "home_name": "Arizona Diamondbacks",
    "away_name": "St. Louis Cardinals",
    "pick_abbr": "ARI",
    "pick": "Arizona Diamondbacks",
    "confidence": 0.6460387111526646,
    "pick_odds": -118,
    "home_pitcher": "Brandon Pfaadt",
    "away_pitcher": "Dustin May",
    "game_id": 825059,
    "result": null
  },
  {
    "home_abbr": "ATL",
    "away_abbr": "TEX",
    "home_name": "Atlanta Braves",
    "away_name": "Texas Rangers",
    "pick_abbr": "ATL",
    "pick": "Atlanta Braves",
    "confidence": 0.6238816213620361,
    "pick_odds": -114,
    "home_pitcher": "Owen Murphy",
    "away_pitcher": "MacKenzie Gore",
    "game_id": 824899,
    "result": null
  },
  {
    "home_abbr": "SEA",
    "away_abbr": "SFG",
    "home_name": "Seattle Mariners",
    "away_name": "San Francisco Giants",
    "pick_abbr": "SEA",
    "pick": "Seattle Mariners",
    "confidence": 0.6196433016044804,
    "pick_odds": -141,
    "home_pitcher": "Bryan Woo",
    "away_pitcher": "Logan Webb",
    "game_id": 823116,
    "result": null
  },
  {
    "home_abbr": "MIL",
    "away_abbr": "MIA",
    "home_name": "Milwaukee Brewers",
    "away_name": "Miami Marlins",
    "pick_abbr": "MIL",
    "pick": "Milwaukee Brewers",
    "confidence": 0.6061104324084285,
    "pick_odds": -146,
    "home_pitcher": "Shane Drohan",
    "away_pitcher": "Max Meyer",
    "game_id": 823763,
    "result": null
  },
  {
    "home_abbr": "PHI",
    "away_abbr": "NYM",
    "home_name": "Philadelphia Phillies",
    "away_name": "New York Mets",
    "pick_abbr": "NYM",
    "pick": "New York Mets",
    "confidence": 0.6035694830647049,
    "pick_odds": 147,
    "home_pitcher": "Jes\u00fas Luzardo",
    "away_pitcher": "Sean Manaea",
    "game_id": 823441,
    "result": null
  },
  {
    "home_abbr": "BOS",
    "away_abbr": "TBR",
    "home_name": "Boston Red Sox",
    "away_name": "Tampa Bay Rays",
    "pick_abbr": "TBR",
    "pick": "Tampa Bay Rays",
    "confidence": 0.5891496579201208,
    "pick_odds": -108,
    "home_pitcher": "Patrick Sandoval",
    "away_pitcher": "Ian Seymour",
    "game_id": 824738,
    "result": null
  },
  {
    "home_abbr": "ATH",
    "away_abbr": "WSN",
    "home_name": "Athletics",
    "away_name": "Washington Nationals",
    "pick_abbr": "WSN",
    "pick": "Washington Nationals",
    "confidence": 0.5837405213184378,
    "pick_odds": 105,
    "home_pitcher": "J.T. Ginn",
    "away_pitcher": "Zack Littell",
    "game_id": 824979,
    "result": null
  },
  {
    "home_abbr": "TOR",
    "away_abbr": "CHW",
    "home_name": "Toronto Blue Jays",
    "away_name": "Chicago White Sox",
    "pick_abbr": "CHW",
    "pick": "Chicago White Sox",
    "confidence": 0.5658051207289378,
    "pick_odds": -107,
    "home_pitcher": "Shane Bieber",
    "away_pitcher": "Davis Martin",
    "game_id": 822790,
    "result": null
  },
  {
    "home_abbr": "KCR",
    "away_abbr": "SDP",
    "home_name": "Kansas City Royals",
    "away_name": "San Diego Padres",
    "pick_abbr": "KCR",
    "pick": "Kansas City Royals",
    "confidence": 0.5596013564719758,
    "pick_odds": -39,
    "home_pitcher": "Randy Dobnak",
    "away_pitcher": "Griffin Canning",
    "game_id": 824088,
    "result": null
  },
  {
    "home_abbr": "LAA",
    "away_abbr": "DET",
    "home_name": "Los Angeles Angels",
    "away_name": "Detroit Tigers",
    "pick_abbr": "DET",
    "pick": "Detroit Tigers",
    "confidence": 0.5553956185743607,
    "pick_odds": -198,
    "home_pitcher": "Grayson Rodriguez",
    "away_pitcher": "Tarik Skubal",
    "game_id": 824008,
    "result": null
  },
  {
    "home_abbr": "CHC",
    "away_abbr": "MIN",
    "home_name": "Chicago Cubs",
    "away_name": "Minnesota Twins",
    "pick_abbr": "MIN",
    "pick": "Minnesota Twins",
    "confidence": 0.537221788560783,
    "pick_odds": 120,
    "home_pitcher": "Matthew Boyd",
    "away_pitcher": "Taj Bradley",
    "game_id": 824657,
    "result": null
  },
  {
    "home_abbr": "HOU",
    "away_abbr": "BAL",
    "home_name": "Houston Astros",
    "away_name": "Baltimore Orioles",
    "pick_abbr": "HOU",
    "pick": "Houston Astros",
    "confidence": 0.5138575017452239,
    "pick_odds": -109,
    "home_pitcher": "Spencer Arrighetti",
    "away_pitcher": "Trevor Rogers",
    "game_id": 824169,
    "result": null
  },
  {
    "home_abbr": "CLE",
    "away_abbr": "PIT",
    "home_name": "Cleveland Guardians",
    "away_name": "Pittsburgh Pirates",
    "pick_abbr": "CLE",
    "pick": "Cleveland Guardians",
    "confidence": 0.507125780128422,
    "pick_odds": -105,
    "home_pitcher": "Logan Allen",
    "away_pitcher": "TBD",
    "game_id": 824414,
    "result": null
  },
  {
    "home_abbr": "CLE",
    "away_abbr": "PIT",
    "home_name": "Cleveland Guardians",
    "away_name": "Pittsburgh Pirates",
    "pick_abbr": "CLE",
    "pick": "Cleveland Guardians",
    "confidence": 0.507125780128422,
    "pick_odds": -105,
    "home_pitcher": "Logan Allen",
    "away_pitcher": "TBD",
    "game_id": 824412,
    "result": null
  }
]