[
  {
    "home_abbr": "WSN",
    "away_abbr": "NYM",
    "home_name": "Washington Nationals",
    "away_name": "New York Mets",
    "pick_abbr": "NYM",
    "pick": "New York Mets",
    "confidence": 0.7394284929301118,
    "pick_odds": -143,
    "home_pitcher": "Foster Griffin",
    "away_pitcher": "Nolan McLean",
    "game_id": 822736,
    "result": null
  },
  {
    "home_abbr": "CHC",
    "away_abbr": "MIL",
    "home_name": "Chicago Cubs",
    "away_name": "Milwaukee Brewers",
    "pick_abbr": "MIL",
    "pick": "Milwaukee Brewers",
    "confidence": 0.668719888762185,
    "pick_odds": -116,
    "home_pitcher": "Ben Brown",
    "away_pitcher": "Jacob Misiorowski",
    "game_id": 824677,
    "result": null
  },
  {
    "home_abbr": "KCR",
    "away_abbr": "BOS",
    "home_name": "Kansas City Royals",
    "away_name": "Boston Red Sox",
    "pick_abbr": "KCR",
    "pick": "Kansas City Royals",
    "confidence": 0.658036339465596,
    "pick_odds": 110,
    "home_pitcher": "Bailey Falter",
    "away_pitcher": "Ranger Suarez",
    "game_id": 824112,
    "result": null
  },
  {
    "home_abbr": "ARI",
    "away_abbr": "SFG",
    "home_name": "Arizona Diamondbacks",
    "away_name": "San Francisco Giants",
    "pick_abbr": "ARI",
    "pick": "Arizona Diamondbacks",
    "confidence": 0.6448521331600521,
    "pick_odds": -120,
    "home_pitcher": "Ryne Nelson",
    "away_pitcher": "Landen Roupp",
    "game_id": 825086,
    "result": null
  },
  {
    "home_abbr": "NYY",
    "away_abbr": "TOR",
    "home_name": "New York Yankees",
    "away_name": "Toronto Blue Jays",
    "pick_abbr": "NYY",
    "pick": "New York Yankees",
    "confidence": 0.5876490430760817,
    "pick_odds": -137,
    "home_pitcher": "Will Warren",
    "away_pitcher": "Dylan Cease",
    "game_id": 823548,
    "result": null
  },
  {
    "home_abbr": "MIA",
    "away_abbr": "ATL",
    "home_name": "Miami Marlins",
    "away_name": "Atlanta Braves",
    "pick_abbr": "MIA",
    "pick": "Miami Marlins",
    "confidence": 0.580741777896618,
    "pick_odds": 117,
    "home_pitcher": "Braxton Garrett",
    "away_pitcher": "Mart\u00edn P\u00e9rez",
    "game_id": 823865,
    "result": null
  },
  {
    "home_abbr": "SEA",
    "away_abbr": "CHW",
    "home_name": "Seattle Mariners",
    "away_name": "Chicago White Sox",
    "pick_abbr": "CHW",
    "pick": "Chicago White Sox",
    "confidence": 0.5518471314044062,
    "pick_odds": 127,
    "home_pitcher": "Bryce Miller",
    "away_pitcher": "Anthony Kay",
    "game_id": 823136,
    "result": null
  },
  {
    "home_abbr": "COL",
    "away_abbr": "TEX",
    "home_name": "Colorado Rockies",
    "away_name": "Texas Rangers",
    "pick_abbr": "TEX",
    "pick": "Texas Rangers",
    "confidence": 0.540168496966362,
    "pick_odds": -109,
    "home_pitcher": "Sammy Peralta",
    "away_pitcher": "Tyler Alexander",
    "game_id": 824356,
    "result": null
  },
  {
    "home_abbr": "DET",
    "away_abbr": "CLE",
    "home_name": "Detroit Tigers",
    "away_name": "Cleveland Guardians",
    "pick_abbr": "CLE",
    "pick": "Cleveland Guardians",
    "confidence": 0.5256284352574461,
    "pick_odds": -163,
    "home_pitcher": "Keider Montero",
    "away_pitcher": "Parker Messick",
    "game_id": 824276,
    "result": null
  },
  {
    "home_abbr": "STL",
    "away_abbr": "PIT",
    "home_name": "St. Louis Cardinals",
    "away_name": "Pittsburgh Pirates",
    "pick_abbr": "PIT",
    "pick": "Pittsburgh Pirates",
    "confidence": 0.5207183326233146,
    "pick_odds": -101,
    "home_pitcher": "Matthew Liberatore",
    "away_pitcher": "Mitch Keller",
    "game_id": 823059,
    "result": null
  },
  {
    "home_abbr": "SDP",
    "away_abbr": "LAD",
    "home_name": "San Diego Padres",
    "away_name": "Los Angeles Dodgers",
    "pick_abbr": "SDP",
    "pick": "San Diego Padres",
    "confidence": 0.5173589769356539,
    "pick_odds": 134,
    "home_pitcher": "Griffin Canning",
    "away_pitcher": "Emmet Sheehan",
    "game_id": 823302,
    "result": null
  },
  {
    "home_abbr": "PHI",
    "away_abbr": "CIN",
    "home_name": "Philadelphia Phillies",
    "away_name": "Cincinnati Reds",
    "pick_abbr": "CIN",
    "pick": "Cincinnati Reds",
    "confidence": 0.5125088291642812,
    "pick_odds": 124,
    "home_pitcher": "Jes\u00fas Luzardo",
    "away_pitcher": "Chase Burns",
    "game_id": 823464,
    "result": null
  },
  {
    "home_abbr": "MIN",
    "away_abbr": "HOU",
    "home_name": "Minnesota Twins",
    "away_name": "Houston Astros",
    "pick_abbr": "HOU",
    "pick": "Houston Astros",
    "confidence": 0.510368859791012,
    "pick_odds": 113,
    "home_pitcher": "Zebby Matthews",
    "away_pitcher": "Lance McCullers Jr.",
    "game_id": 823704,
    "result": null
  },
  {
    "home_abbr": "TBR",
    "away_abbr": "BAL",
    "home_name": "Tampa Bay Rays",
    "away_name": "Baltimore Orioles",
    "pick_abbr": "TBR",
    "pick": "Tampa Bay Rays",
    "confidence": 0.5084390242545619,
    "pick_odds": -110,
    "home_pitcher": "Griffin Jax",
    "away_pitcher": "Kyle Bradish",
    "game_id": 822979,
    "result": null
  },
  {
    "home_abbr": "LAA",
    "away_abbr": "ATH",
    "home_name": "Los Angeles Angels",
    "away_name": "Athletics",
    "pick_abbr": "ATH",
    "pick": "Athletics",
    "confidence": 0.501649561164278,
    "pick_odds": 113,
    "home_pitcher": "Reid Detmers",
    "away_pitcher": "Jacob Lopez",
    "game_id": 824033,
    "result": null
  }
]